{
  "InstanceID": -28676,
  "ID": 610,
  "JournalNumber": 33,
  "Name": "Ice Blob",
  "TypesName": "Slime",
  "TypesArray": [
    10
  ],
  "IsSpectralFamiliar": false,
  "ExploreAbilityName": "Freeze",
  "ExploreAbilityDescription": "- Activates ice orbs",
  "HasSonarAbility": false,
  "BaseStats": {
    "attack": 1,
    "magic": 6,
    "defense": 3,
    "health": 4,
    "mana": 6
  },
  "LightShiftStats": {
    "attack": 0,
    "magic": 3,
    "defense": 1,
    "health": 1,
    "mana": 1
  },
  "DarkShiftStats": {
    "attack": 0,
    "magic": 2,
    "defense": 1,
    "health": 2,
    "mana": 1
  },
  "LightShiftPassive": {
    "ID": 902,
    "Name": "Light Instinct",
    "Description": "Decrease damage taken by 15%.",
    "IsPassiveSkill": true,
    "PassiveSkillProperties": {
      "Description": "Decrease damage taken by {0%}.",
      "IsAura": false,
      "IsUnique": false
    },
    "IsPassiveImproveStat": true,
    "PassiveImproveStatProperties": {
      "IsOnCalculateBaseStats": true,
      "IsOnCalculateStats": true,
      "Stat": 10,
      "Value": 0.15,
      "IsPercent": true,
      "IsNegative": true
    }
  },
  "DarkShiftPassive": {
    "ID": 1905,
    "Name": "Shadow Proc",
    "Description": "Every action applies an additional damage hit (75% Attack or Magic), shield (75% Defense), heal (7.5% Max Health) or a random Buff, depending on action type.",
    "IsPassiveSkill": true,
    "PassiveSkillProperties": {
      "Description": "Every action applies an additional damage hit ({0%} Attack or Magic), shield ({1%} Defense), heal ({2%} Max Health) or a random Buff, depending on action type.",
      "IsAura": false,
      "IsUnique": false
    },
    "IsPassiveShadowProc": true,
    "PassiveShadowProcProperties": {
      "IsOnActionDamageStarted": true,
      "IsOnActionHealStarted": true,
      "IsOnActionShieldStarted": true,
      "IsOnActionBuffStarted": true,
      "DamageValue": 0.75,
      "AnimElement": null,
      "ShieldValue": 0.75,
      "HealValue": 0.075
    }
  },
  "BaseSkills": [
    {
      "ID": 615,
      "Name": "Freeze",
      "Description": "5 x 30% (150%) magical damage (water) Applies Chill (Debuff)",
      "IsBaseAction": true,
      "BaseActionProperties": {
        "Tier": 1,
        "Ultimate": false,
        "Mana": 60,
        "TargetType": 0,
        "Duration": 2.6,
        "IsDefaultAction": false,
        "Tooltip": "",
        "ParentAction": null,
        "SpecialAttackAnimation": false,
        "IsPotion": false
      },
      "IsActionModifier": true,
      "ActionModifierProperties": {},
      "IsActionDamage": true,
      "ActionDamageProperties": {
        "DamageMultiplicator": 0.3,
        "TotalDamage": 1.5,
        "CalculatedDamage": 0.3,
        "CalculatedTotalDamage": 1.5,
        "HitTimings": [
          1.2,
          1.5,
          1.8,
          2.1,
          2.4
        ],
        "Element": 2,
        "Type": 1,
        "FlashDuration": 0.2,
        "MultipleEnemiesDelay": 0.2,
        "CritDamageBonus": 0.0,
        "DefenseBypass": 0.0,
        "DefenseBypassBurnCondition": false,
        "PlayHitAnimation": false,
        "TriggersBleed": false,
        "CannotBeDodged": false,
        "TriggersAllShocks": false,
        "LifestealAmount": 0.0,
        "GravityMultiplier": 0.0,
        "BuffMultiplier": 0.0
      },
      "IsActionDebuff": true,
      "ActionDebuffProperties": {
        "Debuffs": [
          3
        ],
        "ApplyDelay": 0.7,
        "ApplyChance": 1.0,
        "TargetCount": 1
      }
    },
    {
      "ID": 611,
      "Name": "Chilling Wind",
      "Description": "4 x 40% (160%) magical damage (wind) Applies Chill (Debuff)",
      "IsBaseAction": true,
      "BaseActionProperties": {
        "Tier": 1,
        "Ultimate": false,
        "Mana": 60,
        "TargetType": 0,
        "Duration": 2.0,
        "IsDefaultAction": false,
        "Tooltip": "",
        "ParentAction": null,
        "SpecialAttackAnimation": false,
        "IsPotion": false
      },
      "IsActionModifier": true,
      "ActionModifierProperties": {},
      "IsActionDamage": true,
      "ActionDamageProperties": {
        "DamageMultiplicator": 0.4,
        "TotalDamage": 1.6,
        "CalculatedDamage": 0.4,
        "CalculatedTotalDamage": 1.6,
        "HitTimings": [
          0.5,
          0.8,
          1.1,
          1.4
        ],
        "Element": 3,
        "Type": 1,
        "FlashDuration": 0.4,
        "MultipleEnemiesDelay": 0.2,
        "CritDamageBonus": 0.0,
        "DefenseBypass": 0.0,
        "DefenseBypassBurnCondition": false,
        "PlayHitAnimation": true,
        "TriggersBleed": false,
        "CannotBeDodged": false,
        "TriggersAllShocks": false,
        "LifestealAmount": 0.0,
        "GravityMultiplier": 0.0,
        "BuffMultiplier": 0.0
      },
      "IsActionDebuff": true,
      "ActionDebuffProperties": {
        "Debuffs": [
          3
        ],
        "ApplyDelay": 1.7,
        "ApplyChance": 1.0,
        "TargetCount": 1
      }
    },
    {
      "ID": 194,
      "Name": "Fire Weakness",
      "Description": "Fire damage increased by 50%",
      "IsPassiveSkill": true,
      "PassiveSkillProperties": {
        "Description": "Fire damage increased by {50%}",
        "IsAura": false,
        "IsUnique": false
      },
      "IsPassiveElementModifier": true,
      "PassiveElementModifierProperties": {
        "Element": 1,
        "Modifier": 0.5
      }
    },
    {
      "ID": 275,
      "Name": "Water Resistance",
      "Description": "Water damage reduced by 50%",
      "IsPassiveSkill": true,
      "PassiveSkillProperties": {
        "Description": "Water damage reduced by {50%}",
        "IsAura": false,
        "IsUnique": false
      },
      "IsPassiveElementModifier": true,
      "PassiveElementModifierProperties": {
        "Element": 2,
        "Modifier": -0.5
      }
    }
  ],
  "SkillTrees": [
    {
      "Tier1Skills": [
        {
          "ID": 615,
          "Name": "Freeze",
          "Description": "5 x 30% (150%) magical damage (water) Applies Chill (Debuff)",
          "IsBaseAction": true,
          "BaseActionProperties": {
            "Tier": 1,
            "Ultimate": false,
            "Mana": 60,
            "TargetType": 0,
            "Duration": 2.6,
            "IsDefaultAction": false,
            "Tooltip": "",
            "ParentAction": null,
            "SpecialAttackAnimation": false,
            "IsPotion": false
          },
          "IsActionModifier": true,
          "ActionModifierProperties": {},
          "IsActionDamage": true,
          "ActionDamageProperties": {
            "DamageMultiplicator": 0.3,
            "TotalDamage": 1.5,
            "CalculatedDamage": 0.3,
            "CalculatedTotalDamage": 1.5,
            "HitTimings": [
              1.2,
              1.5,
              1.8,
              2.1,
              2.4
            ],
            "Element": 2,
            "Type": 1,
            "FlashDuration": 0.2,
            "MultipleEnemiesDelay": 0.2,
            "CritDamageBonus": 0.0,
            "DefenseBypass": 0.0,
            "DefenseBypassBurnCondition": false,
            "PlayHitAnimation": false,
            "TriggersBleed": false,
            "CannotBeDodged": false,
            "TriggersAllShocks": false,
            "LifestealAmount": 0.0,
            "GravityMultiplier": 0.0,
            "BuffMultiplier": 0.0
          },
          "IsActionDebuff": true,
          "ActionDebuffProperties": {
            "Debuffs": [
              3
            ],
            "ApplyDelay": 0.7,
            "ApplyChance": 1.0,
            "TargetCount": 1
          }
        }
      ],
      "Tier2Skills": [
        {
          "ID": 617,
          "Name": "Freeze Lvl 2",
          "Description": "5 x 40% (200%) magical damage (water) Applies Chill (Debuff)",
          "IsBaseAction": true,
          "BaseActionProperties": {
            "Tier": 2,
            "Ultimate": false,
            "Mana": 90,
            "TargetType": 0,
            "Duration": 2.6,
            "IsDefaultAction": false,
            "Tooltip": "",
            "ParentAction": 615,
            "SpecialAttackAnimation": false,
            "IsPotion": false
          },
          "IsActionModifier": true,
          "ActionModifierProperties": {},
          "IsActionDamage": true,
          "ActionDamageProperties": {
            "DamageMultiplicator": 0.4,
            "TotalDamage": 2.0,
            "CalculatedDamage": 0.408,
            "CalculatedTotalDamage": 2.04,
            "HitTimings": [
              1.2,
              1.5,
              1.8,
              2.1,
              2.4
            ],
            "Element": 2,
            "Type": 1,
            "FlashDuration": 0.2,
            "MultipleEnemiesDelay": 0.2,
            "CritDamageBonus": 0.0,
            "DefenseBypass": 0.0,
            "DefenseBypassBurnCondition": false,
            "PlayHitAnimation": false,
            "TriggersBleed": false,
            "CannotBeDodged": false,
            "TriggersAllShocks": false,
            "LifestealAmount": 0.0,
            "GravityMultiplier": 0.0,
            "BuffMultiplier": 0.0
          },
          "IsActionDebuff": true,
          "ActionDebuffProperties": {
            "Debuffs": [
              3
            ],
            "ApplyDelay": 0.7,
            "ApplyChance": 1.0,
            "TargetCount": 1
          }
        },
        {
          "ID": 242,
          "Name": "Defense Plus",
          "Description": "Improve Defense rating by 1 (Increases Defense by 36)",
          "IsPassiveSkill": true,
          "PassiveSkillProperties": {
            "Description": "",
            "IsAura": false,
            "IsUnique": false
          },
          "IsPassiveImproveStat": true,
          "PassiveImproveStatProperties": {
            "IsOnCalculateBaseStats": true,
            "IsOnCalculateStats": true,
            "Stat": 2,
            "Value": 1.0,
            "IsPercent": false,
            "IsNegative": false
          }
        },
        {
          "ID": 620,
          "Name": "Initial Chill",
          "Description": "Apply Chill (Debuff) to a random enemy at the start of combat.",
          "IsPassiveSkill": true,
          "PassiveSkillProperties": {
            "OverlayDebuffs": [
              3
            ],
            "Description": "Apply {Chill} (Debuff) to a random enemy at the start of combat.",
            "IsAura": false,
            "IsUnique": false
          },
          "IsPassiveStartCombatDebuff": true,
          "PassiveStartCombatDebuffProperties": {
            "IsOnCombatStart": true,
            "Debuff": 3
          }
        }
      ],
      "Tier3Skills": [
        {
          "ID": 616,
          "Name": "Freeze Lvl 3",
          "Description": "6 x 45% (270%) magical damage (water) Applies Chill (Debuff)",
          "IsBaseAction": true,
          "BaseActionProperties": {
            "Tier": 3,
            "Ultimate": false,
            "Mana": 130,
            "TargetType": 0,
            "Duration": 2.6,
            "IsDefaultAction": false,
            "Tooltip": "",
            "ParentAction": 617,
            "SpecialAttackAnimation": false,
            "IsPotion": false
          },
          "IsActionModifier": true,
          "ActionModifierProperties": {},
          "IsActionDamage": true,
          "ActionDamageProperties": {
            "DamageMultiplicator": 0.45,
            "TotalDamage": 2.69999981,
            "CalculatedDamage": 0.44025,
            "CalculatedTotalDamage": 2.6415,
            "HitTimings": [
              1.15,
              1.4,
              1.65,
              1.9,
              2.15,
              2.4
            ],
            "Element": 2,
            "Type": 1,
            "FlashDuration": 0.2,
            "MultipleEnemiesDelay": 0.2,
            "CritDamageBonus": 0.0,
            "DefenseBypass": 0.0,
            "DefenseBypassBurnCondition": false,
            "PlayHitAnimation": false,
            "TriggersBleed": false,
            "CannotBeDodged": false,
            "TriggersAllShocks": false,
            "LifestealAmount": 0.0,
            "GravityMultiplier": 0.0,
            "BuffMultiplier": 0.0
          },
          "IsActionDebuff": true,
          "ActionDebuffProperties": {
            "Debuffs": [
              3
            ],
            "ApplyDelay": 0.7,
            "ApplyChance": 1.0,
            "TargetCount": 1
          }
        },
        {
          "ID": 117,
          "Name": "Magic Plus",
          "Description": "Improve Magic rating by 1 (Increases Magic by 26)",
          "IsPassiveSkill": true,
          "PassiveSkillProperties": {
            "Description": "",
            "IsAura": false,
            "IsUnique": false
          },
          "IsPassiveImproveStat": true,
          "PassiveImproveStatProperties": {
            "IsOnCalculateBaseStats": true,
            "IsOnCalculateStats": true,
            "Stat": 1,
            "Value": 1.0,
            "IsPercent": false,
            "IsNegative": false
          }
        },
        {
          "ID": 893,
          "Name": "Congeal",
          "Description": "Unique Aura: Chill (Debuff) deals damage to enemies at the start of their turn based on their missing Mana.",
          "IsPassiveSkill": true,
          "PassiveSkillProperties": {
            "Description": "{Chill} (Debuff) deals damage to enemies at the start of their turn based on their missing Mana.",
            "IsAura": true,
            "IsUnique": true
          },
          "IsPassiveCongeal": true,
          "PassiveCongealProperties": {}
        },
        {
          "ID": 1099,
          "Name": "Defense Overload",
          "Description": "Increase Attack and Magic by 15% of this Monster's Defense.",
          "IsPassiveSkill": true,
          "PassiveSkillProperties": {
            "Description": "Increase Attack and Magic by {0%} of this Monster's Defense.",
            "IsAura": false,
            "IsUnique": false
          },
          "IsPassiveImproveStatDependant": true,
          "PassiveImproveStatDependantProperties": {
            "IsOnCalculateStatsPostMultiplication": true,
            "IsOnCalculateTeamMonsterStats": true,
            "DependantStat": 2,
            "IncreasedStat": 8,
            "Value": 0.15,
            "Pass": 1
          }
        },
        {
          "ID": 534,
          "Name": "Multi Chill",
          "Description": "Aura: Chill (Debuff) can be stacked two additional times on enemies. Additional stacks are only half as strong.",
          "IsPassiveSkill": true,
          "PassiveSkillProperties": {
            "Description": "{Chill} (Debuff) can be stacked two additional times on enemies. Additional stacks are only half as strong.",
            "IsAura": true,
            "IsUnique": false
          },
          "IsPassiveIncreaseDebuffStacks": true,
          "PassiveIncreaseDebuffStacksProperties": {
            "stackCountIncrease": 2,
            "Debuff": 3
          }
        }
      ],
      "Tier4Skills": [
        {
          "ID": 624,
          "Name": "Freeze Lvl 4",
          "Description": "6 x 60% (360%) magical damage (water) Applies Chill (Debuff)",
          "IsBaseAction": true,
          "BaseActionProperties": {
            "Tier": 4,
            "Ultimate": false,
            "Mana": 180,
            "TargetType": 0,
            "Duration": 2.6,
            "IsDefaultAction": false,
            "Tooltip": "",
            "ParentAction": 616,
            "SpecialAttackAnimation": false,
            "IsPotion": false
          },
          "IsActionModifier": true,
          "ActionModifierProperties": {},
          "IsActionDamage": true,
          "ActionDamageProperties": {
            "DamageMultiplicator": 0.6,
            "TotalDamage": 3.60000014,
            "CalculatedDamage": 0.5865458,
            "CalculatedTotalDamage": 3.519275,
            "HitTimings": [
              1.15,
              1.4,
              1.65,
              1.9,
              2.15,
              2.4
            ],
            "Element": 2,
            "Type": 1,
            "FlashDuration": 0.2,
            "MultipleEnemiesDelay": 0.2,
            "CritDamageBonus": 0.0,
            "DefenseBypass": 0.0,
            "DefenseBypassBurnCondition": false,
            "PlayHitAnimation": false,
            "TriggersBleed": false,
            "CannotBeDodged": false,
            "TriggersAllShocks": false,
            "LifestealAmount": 0.0,
            "GravityMultiplier": 0.0,
            "BuffMultiplier": 0.0
          },
          "IsActionDebuff": true,
          "ActionDebuffProperties": {
            "Debuffs": [
              3
            ],
            "ApplyDelay": 0.7,
            "ApplyChance": 1.0,
            "TargetCount": 1
          }
        },
        {
          "ID": 840,
          "Name": "Deep Freeze",
          "Description": "4 x 85% (340%) magical damage (water) Deals an additional 40% hit for every Chill on the target",
          "IsBaseAction": true,
          "BaseActionProperties": {
            "Tier": 4,
            "Ultimate": false,
            "Mana": 160,
            "TargetType": 0,
            "Duration": 2.7,
            "IsDefaultAction": false,
            "Tooltip": "",
            "ParentAction": null,
            "SpecialAttackAnimation": false,
            "IsPotion": false
          },
          "IsActionModifier": true,
          "ActionModifierProperties": {},
          "IsActionConditionalDamage": true,
          "ActionConditionalDamageProperties": {
            "requiredDebuff": 3,
            "HitForEveryDebuffStack": true,
            "PerHitDelay": 0.2,
            "DamageMultiplicator": 0.4,
            "HitTimings": [
              2.4
            ],
            "DurationIncrease": 0.0,
            "AnimElement": null,
            "FlippedAnimElement": null,
            "AnimElementDelay": 2.3
          },
          "IsActionDamage": true,
          "ActionDamageProperties": {
            "DamageMultiplicator": 0.85,
            "TotalDamage": 3.4,
            "CalculatedDamage": 0.934743643,
            "CalculatedTotalDamage": 3.73897457,
            "HitTimings": [
              0.7,
              1.0,
              1.3,
              1.6
            ],
            "Element": 2,
            "Type": 1,
            "FlashDuration": 0.2,
            "MultipleEnemiesDelay": 0.2,
            "CritDamageBonus": 0.0,
            "DefenseBypass": 0.0,
            "DefenseBypassBurnCondition": false,
            "PlayHitAnimation": false,
            "TriggersBleed": false,
            "CannotBeDodged": false,
            "TriggersAllShocks": false,
            "LifestealAmount": 0.0,
            "GravityMultiplier": 0.0,
            "BuffMultiplier": 0.0
          }
        },
        {
          "ID": 2061,
          "Name": "Severe Cold",
          "Description": "Unique Aura: Whenever an enemy takes Congeal damage, 65% chance to inflict a Wound stack on them.",
          "IsPassiveSkill": true,
          "PassiveSkillProperties": {
            "OverlaySpecialBuff": {
              "BuffType": 6,
              "Name": "Wound",
              "Icon": "wound",
              "Description": "Reduces all healing this Monster receives by 40%. Removed at the end of the turn after healing was received.",
              "IsNegative": true
            },
            "Description": "Whenever an enemy takes {Congeal} damage, {0%} chance to inflict a {Wound} stack on them.",
            "IsAura": true,
            "IsUnique": true
          },
          "IsPassiveSevereNature": true,
          "PassiveSevereNatureProperties": {
            "IsOnTriggerCongealDamage": true,
            "TriggerChance": 0.65
          }
        },
        {
          "ID": 623,
          "Name": "Defense Focus",
          "Description": "Defense from equipment increased by 25%.",
          "IsPassiveSkill": true,
          "PassiveSkillProperties": {
            "Description": "Defense from equipment increased by {0%}.",
            "IsAura": false,
            "IsUnique": false
          },
          "IsPassiveEquipmentFocus": true,
          "PassiveEquipmentFocusProperties": {
            "Stat": 2,
            "Bonus": 0.25
          }
        },
        {
          "ID": 1924,
          "Name": "Reckless Mending",
          "Description": "Unique Aura: When an ally applies Armor Break or Chill, it regains 3% of Max Health and Max Mana.",
          "IsPassiveSkill": true,
          "PassiveSkillProperties": {
            "Description": "When an ally applies {Armor Break} or {Chill}, it regains {0%} of Max Health and Max Mana.",
            "IsAura": true,
            "IsUnique": true
          },
          "IsPassiveRecklessMending": true,
          "PassiveRecklessMendingProperties": {
            "IsOnAllyApplyDebuffToEnemy": true,
            "HealAmount": 0.03
          }
        }
      ],
      "Tier5Skills": [
        {
          "ID": 1279,
          "Name": "Freeze Lvl 5",
          "Description": "7 x 60% (420%) magical damage (water) Applies Chill (Debuff)",
          "IsBaseAction": true,
          "BaseActionProperties": {
            "Tier": 5,
            "Ultimate": false,
            "Mana": 220,
            "TargetType": 0,
            "Duration": 2.9,
            "IsDefaultAction": false,
            "Tooltip": "",
            "ParentAction": 624,
            "SpecialAttackAnimation": false,
            "IsPotion": false
          },
          "IsActionModifier": true,
          "ActionModifierProperties": {},
          "IsActionDamage": true,
          "ActionDamageProperties": {
            "DamageMultiplicator": 0.6,
            "TotalDamage": 4.20000029,
            "CalculatedDamage": 0.6130351,
            "CalculatedTotalDamage": 4.29124546,
            "HitTimings": [
              1.15,
              1.4,
              1.65,
              1.9,
              2.15,
              2.4,
              2.65
            ],
            "Element": 2,
            "Type": 1,
            "FlashDuration": 0.2,
            "MultipleEnemiesDelay": 0.2,
            "CritDamageBonus": 0.0,
            "DefenseBypass": 0.0,
            "DefenseBypassBurnCondition": false,
            "PlayHitAnimation": false,
            "TriggersBleed": false,
            "CannotBeDodged": false,
            "TriggersAllShocks": false,
            "LifestealAmount": 0.0,
            "GravityMultiplier": 0.0,
            "BuffMultiplier": 0.0
          },
          "IsActionDebuff": true,
          "ActionDebuffProperties": {
            "Debuffs": [
              3
            ],
            "ApplyDelay": 0.7,
            "ApplyChance": 1.0,
            "TargetCount": 1
          }
        },
        {
          "ID": 1278,
          "Name": "Deep Freeze Lvl 2",
          "Description": "4 x 110% (440%) magical damage (water) Deals an additional 40% hit for every Chill on the target",
          "IsBaseAction": true,
          "BaseActionProperties": {
            "Tier": 5,
            "Ultimate": false,
            "Mana": 210,
            "TargetType": 0,
            "Duration": 2.7,
            "IsDefaultAction": false,
            "Tooltip": "",
            "ParentAction": 840,
            "SpecialAttackAnimation": false,
            "IsPotion": false
          },
          "IsActionModifier": true,
          "ActionModifierProperties": {},
          "IsActionConditionalDamage": true,
          "ActionConditionalDamageProperties": {
            "requiredDebuff": 3,
            "HitForEveryDebuffStack": true,
            "PerHitDelay": 0.2,
            "DamageMultiplicator": 0.4,
            "HitTimings": [
              2.4
            ],
            "DurationIncrease": 0.0,
            "AnimElement": null,
            "FlippedAnimElement": null,
            "AnimElementDelay": 2.3
          },
          "IsActionDamage": true,
          "ActionDamageProperties": {
            "DamageMultiplicator": 1.1,
            "TotalDamage": 4.4,
            "CalculatedDamage": 1.19421387,
            "CalculatedTotalDamage": 4.77685547,
            "HitTimings": [
              0.7,
              1.0,
              1.3,
              1.6
            ],
            "Element": 2,
            "Type": 1,
            "FlashDuration": 0.2,
            "MultipleEnemiesDelay": 0.2,
            "CritDamageBonus": 0.0,
            "DefenseBypass": 0.0,
            "DefenseBypassBurnCondition": false,
            "PlayHitAnimation": false,
            "TriggersBleed": false,
            "CannotBeDodged": false,
            "TriggersAllShocks": false,
            "LifestealAmount": 0.0,
            "GravityMultiplier": 0.0,
            "BuffMultiplier": 0.0
          }
        },
        {
          "ID": 2015,
          "Name": "Severe Infection",
          "Description": "Aura: Debuffs are 10% more effective against Wounded enemies.",
          "IsPassiveSkill": true,
          "PassiveSkillProperties": {
            "Description": "Debuffs are {0%} more effective against {Wounded} enemies.",
            "IsAura": true,
            "IsUnique": false
          },
          "IsPassiveSevereInfection": true,
          "PassiveSevereInfectionProperties": {
            "IsOnCalculateEnemyStats": true,
            "DebuffModifier": 0.1
          }
        },
        {
          "ID": 219,
          "Name": "Cascade",
          "Description": "The power of every consecutive hit during an ability is increased by 5% continuously. (For a 4 hit attack: +0%, +5%, +10%, +15%)",
          "IsPassiveSkill": true,
          "PassiveSkillProperties": {
            "Description": "The power of every consecutive hit during an ability is increased by {0%} continuously. (For a 4 hit attack: +0%, +5%, +10%, +15%)",
            "IsAura": false,
            "IsUnique": false
          },
          "IsPassiveCascade": true,
          "PassiveCascadeProperties": {
            "IsOnActionDamageHit": true,
            "IsOnActionHealTarget": true,
            "IsOnActionShieldTarget": true,
            "DamageBonus": 0.05
          }
        },
        {
          "ID": 175,
          "Name": "Mana Plus",
          "Description": "Improve Mana rating by 1 (Increases Mana by 20. Increases Mana Regeneration by 11)",
          "IsPassiveSkill": true,
          "PassiveSkillProperties": {
            "Description": "",
            "IsAura": false,
            "IsUnique": false
          },
          "IsPassiveImproveStat": true,
          "PassiveImproveStatProperties": {
            "IsOnCalculateBaseStats": true,
            "IsOnCalculateStats": true,
            "Stat": 4,
            "Value": 1.0,
            "IsPercent": false,
            "IsNegative": false
          }
        }
      ]
    },
    {
      "Tier1Skills": [
        {
          "ID": 187,
          "Name": "Arcane Bolt",
          "Description": "4 x 40% (160%) magical damage (neutral)",
          "IsBaseAction": true,
          "BaseActionProperties": {
            "Tier": 1,
            "Ultimate": false,
            "Mana": 30,
            "TargetType": 0,
            "Duration": 2.0,
            "IsDefaultAction": false,
            "Tooltip": "",
            "ParentAction": null,
            "SpecialAttackAnimation": false,
            "IsPotion": false
          },
          "IsActionModifier": true,
          "ActionModifierProperties": {},
          "IsActionDamage": true,
          "ActionDamageProperties": {
            "DamageMultiplicator": 0.4,
            "TotalDamage": 1.6,
            "CalculatedDamage": 0.390000045,
            "CalculatedTotalDamage": 1.56000018,
            "HitTimings": [
              0.5,
              0.9,
              1.3,
              1.7
            ],
            "Element": 0,
            "Type": 1,
            "FlashDuration": 0.2,
            "MultipleEnemiesDelay": 0.2,
            "CritDamageBonus": 0.0,
            "DefenseBypass": 0.0,
            "DefenseBypassBurnCondition": false,
            "PlayHitAnimation": true,
            "TriggersBleed": false,
            "CannotBeDodged": false,
            "TriggersAllShocks": false,
            "LifestealAmount": 0.0,
            "GravityMultiplier": 0.0,
            "BuffMultiplier": 0.0
          }
        }
      ],
      "Tier2Skills": [
        {
          "ID": 111,
          "Name": "Arcane Bolt Lvl 2",
          "Description": "5 x 40% (200%) magical damage (neutral)",
          "IsBaseAction": true,
          "BaseActionProperties": {
            "Tier": 2,
            "Ultimate": false,
            "Mana": 60,
            "TargetType": 0,
            "Duration": 2.0,
            "IsDefaultAction": false,
            "Tooltip": "",
            "ParentAction": 187,
            "SpecialAttackAnimation": false,
            "IsPotion": false
          },
          "IsActionModifier": true,
          "ActionModifierProperties": {},
          "IsActionDamage": true,
          "ActionDamageProperties": {
            "DamageMultiplicator": 0.4,
            "TotalDamage": 2.0,
            "CalculatedDamage": 0.4156,
            "CalculatedTotalDamage": 2.078,
            "HitTimings": [
              0.5,
              0.8,
              1.1,
              1.4,
              1.7
            ],
            "Element": 0,
            "Type": 1,
            "FlashDuration": 0.2,
            "MultipleEnemiesDelay": 0.2,
            "CritDamageBonus": 0.0,
            "DefenseBypass": 0.0,
            "DefenseBypassBurnCondition": false,
            "PlayHitAnimation": true,
            "TriggersBleed": false,
            "CannotBeDodged": false,
            "TriggersAllShocks": false,
            "LifestealAmount": 0.0,
            "GravityMultiplier": 0.0,
            "BuffMultiplier": 0.0
          }
        },
        {
          "ID": 94,
          "Name": "Saboteur's Shield",
          "Description": "Apply Shield equal to 50% of own defense when applying a Debuff.",
          "IsPassiveSkill": true,
          "PassiveSkillProperties": {
            "Description": "Apply Shield equal to {0%} of own defense when applying a Debuff.",
            "IsAura": false,
            "IsUnique": false
          },
          "IsPassiveSaboteursShield": true,
          "PassiveSaboteursShieldProperties": {
            "IsOnApplyDebuffToEnemy": true,
            "Percent": 0.5
          }
        },
        {
          "ID": 117,
          "Name": "Magic Plus",
          "Description": "Improve Magic rating by 1 (Increases Magic by 26)",
          "IsPassiveSkill": true,
          "PassiveSkillProperties": {
            "Description": "",
            "IsAura": false,
            "IsUnique": false
          },
          "IsPassiveImproveStat": true,
          "PassiveImproveStatProperties": {
            "IsOnCalculateBaseStats": true,
            "IsOnCalculateStats": true,
            "Stat": 1,
            "Value": 1.0,
            "IsPercent": false,
            "IsNegative": false
          }
        }
      ],
      "Tier3Skills": [
        {
          "ID": 162,
          "Name": "Arcane Bolt Lvl 3",
          "Description": "6 x 45% (270%) magical damage (neutral)",
          "IsBaseAction": true,
          "BaseActionProperties": {
            "Tier": 3,
            "Ultimate": false,
            "Mana": 90,
            "TargetType": 0,
            "Duration": 2.3,
            "IsDefaultAction": false,
            "Tooltip": "",
            "ParentAction": 111,
            "SpecialAttackAnimation": false,
            "IsPotion": false
          },
          "IsActionModifier": true,
          "ActionModifierProperties": {},
          "IsActionDamage": true,
          "ActionDamageProperties": {
            "DamageMultiplicator": 0.45,
            "TotalDamage": 2.69999981,
            "CalculatedDamage": 0.446816653,
            "CalculatedTotalDamage": 2.68089986,
            "HitTimings": [
              0.5,
              0.8,
              1.1,
              1.4,
              1.7,
              2.0
            ],
            "Element": 0,
            "Type": 1,
            "FlashDuration": 0.2,
            "MultipleEnemiesDelay": 0.2,
            "CritDamageBonus": 0.0,
            "DefenseBypass": 0.0,
            "DefenseBypassBurnCondition": false,
            "PlayHitAnimation": true,
            "TriggersBleed": false,
            "CannotBeDodged": false,
            "TriggersAllShocks": false,
            "LifestealAmount": 0.0,
            "GravityMultiplier": 0.0,
            "BuffMultiplier": 0.0
          }
        },
        {
          "ID": 186,
          "Name": "Ice Storm",
          "Description": "1 x 160% magical damage (water) Hits all enemies, 50% chance to apply Chill (Debuff)",
          "IsBaseAction": true,
          "BaseActionProperties": {
            "Tier": 3,
            "Ultimate": false,
            "Mana": 120,
            "TargetType": 1,
            "Duration": 2.5,
            "IsDefaultAction": false,
            "Tooltip": "",
            "ParentAction": null,
            "SpecialAttackAnimation": false,
            "IsPotion": false
          },
          "IsActionModifier": true,
          "ActionModifierProperties": {},
          "IsActionDamage": true,
          "ActionDamageProperties": {
            "DamageMultiplicator": 1.6,
            "TotalDamage": 1.6,
            "CalculatedDamage": 1.62354982,
            "CalculatedTotalDamage": 1.62354982,
            "HitTimings": [
              2.0
            ],
            "Element": 2,
            "Type": 1,
            "FlashDuration": 0.4,
            "MultipleEnemiesDelay": 0.2,
            "CritDamageBonus": 0.0,
            "DefenseBypass": 0.0,
            "DefenseBypassBurnCondition": false,
            "PlayHitAnimation": false,
            "TriggersBleed": false,
            "CannotBeDodged": false,
            "TriggersAllShocks": false,
            "LifestealAmount": 0.0,
            "GravityMultiplier": 0.0,
            "BuffMultiplier": 0.0
          },
          "IsActionDebuff": true,
          "ActionDebuffProperties": {
            "Debuffs": [
              3
            ],
            "ApplyDelay": 0.8,
            "ApplyChance": 0.5,
            "TargetCount": 1
          }
        },
        {
          "ID": 577,
          "Name": "Magic Proc",
          "Description": "Every attack triggers an additional hit equal to 35% of Magic value.",
          "IsPassiveSkill": true,
          "PassiveSkillProperties": {
            "Description": "Every attack triggers an additional hit equal to {1%} of Magic value.",
            "IsAura": false,
            "IsUnique": false
          },
          "IsPassiveComboMaster": true,
          "PassiveComboMasterProperties": {
            "IsOnAllyActionDamageStarted": true,
            "DamageValue": 0.0,
            "StatScaling": 0.35,
            "ScaleStat": 1,
            "AnimElement": null,
            "ElementRestriction": 8,
            "TypeRestriction": 0
          }
        },
        {
          "ID": 622,
          "Name": "Sheltered",
          "Description": "While under the effect of a Shield, reduce all incoming damage by 15%.",
          "IsPassiveSkill": true,
          "PassiveSkillProperties": {
            "Description": "While under the effect of a Shield, reduce all incoming damage by {0%}.",
            "IsAura": false,
            "IsUnique": false
          },
          "IsPassiveHardShield": true,
          "PassiveHardShieldProperties": {
            "IsOnBeingHit": true,
            "DamageReduction": 0.15
          }
        }
      ],
      "Tier4Skills": [
        {
          "ID": 627,
          "Name": "Arcane Bolt Lvl 4",
          "Description": "7 x 50% (350%) magical damage (neutral)",
          "IsBaseAction": true,
          "BaseActionProperties": {
            "Tier": 4,
            "Ultimate": false,
            "Mana": 130,
            "TargetType": 0,
            "Duration": 2.3,
            "IsDefaultAction": false,
            "Tooltip": "",
            "ParentAction": 162,
            "SpecialAttackAnimation": false,
            "IsPotion": false
          },
          "IsActionModifier": true,
          "ActionModifierProperties": {},
          "IsActionDamage": true,
          "ActionDamageProperties": {
            "DamageMultiplicator": 0.5,
            "TotalDamage": 3.5,
            "CalculatedDamage": 0.498642147,
            "CalculatedTotalDamage": 3.490495,
            "HitTimings": [
              0.5,
              0.75,
              1.0,
              1.25,
              1.5,
              1.75,
              2.0
            ],
            "Element": 0,
            "Type": 1,
            "FlashDuration": 0.2,
            "MultipleEnemiesDelay": 0.2,
            "CritDamageBonus": 0.0,
            "DefenseBypass": 0.0,
            "DefenseBypassBurnCondition": false,
            "PlayHitAnimation": true,
            "TriggersBleed": false,
            "CannotBeDodged": false,
            "TriggersAllShocks": false,
            "LifestealAmount": 0.0,
            "GravityMultiplier": 0.0,
            "BuffMultiplier": 0.0
          }
        },
        {
          "ID": 626,
          "Name": "Ice Storm Lvl 2",
          "Description": "1 x 210% magical damage (water) Hits all enemies, 50% chance to apply Chill (Debuff)",
          "IsBaseAction": true,
          "BaseActionProperties": {
            "Tier": 4,
            "Ultimate": false,
            "Mana": 170,
            "TargetType": 1,
            "Duration": 2.5,
            "IsDefaultAction": false,
            "Tooltip": "",
            "ParentAction": 186,
            "SpecialAttackAnimation": false,
            "IsPotion": false
          },
          "IsActionModifier": true,
          "ActionModifierProperties": {},
          "IsActionDamage": true,
          "ActionDamageProperties": {
            "DamageMultiplicator": 2.1,
            "TotalDamage": 2.1,
            "CalculatedDamage": 2.12327719,
            "CalculatedTotalDamage": 2.12327719,
            "HitTimings": [
              2.0
            ],
            "Element": 2,
            "Type": 1,
            "FlashDuration": 0.4,
            "MultipleEnemiesDelay": 0.2,
            "CritDamageBonus": 0.0,
            "DefenseBypass": 0.0,
            "DefenseBypassBurnCondition": false,
            "PlayHitAnimation": false,
            "TriggersBleed": false,
            "CannotBeDodged": false,
            "TriggersAllShocks": false,
            "LifestealAmount": 0.0,
            "GravityMultiplier": 0.0,
            "BuffMultiplier": 0.0
          },
          "IsActionDebuff": true,
          "ActionDebuffProperties": {
            "Debuffs": [
              3
            ],
            "ApplyDelay": 0.8,
            "ApplyChance": 0.5,
            "TargetCount": 1
          }
        },
        {
          "ID": 78,
          "Name": "Health Plus",
          "Description": "Improve Health rating by 1 (Increases Health by 332)",
          "IsPassiveSkill": true,
          "PassiveSkillProperties": {
            "Description": "",
            "IsAura": false,
            "IsUnique": false
          },
          "IsPassiveImproveStat": true,
          "PassiveImproveStatProperties": {
            "IsOnCalculateBaseStats": true,
            "IsOnCalculateStats": true,
            "Stat": 3,
            "Value": 1.0,
            "IsPercent": false,
            "IsNegative": false
          }
        },
        {
          "ID": 124,
          "Name": "Weaken",
          "Description": "Every hit has a 10% chance to apply Weakness.",
          "IsPassiveSkill": true,
          "PassiveSkillProperties": {
            "OverlayDebuffs": [
              0
            ],
            "Description": "Every hit has a {0%} chance to apply {Weakness}.",
            "IsAura": false,
            "IsUnique": false
          },
          "IsPassiveDebuffChance": true,
          "PassiveDebuffChanceProperties": {
            "IsOnActionDamageHit": true,
            "IsOnCounterAttackHit": true,
            "Debuff": 0,
            "Chance": 0.1,
            "RestrictToElement": false,
            "ElementRestriction": 0
          }
        },
        {
          "ID": 117,
          "Name": "Magic Plus",
          "Description": "Improve Magic rating by 1 (Increases Magic by 26)",
          "IsPassiveSkill": true,
          "PassiveSkillProperties": {
            "Description": "",
            "IsAura": false,
            "IsUnique": false
          },
          "IsPassiveImproveStat": true,
          "PassiveImproveStatProperties": {
            "IsOnCalculateBaseStats": true,
            "IsOnCalculateStats": true,
            "Stat": 1,
            "Value": 1.0,
            "IsPercent": false,
            "IsNegative": false
          }
        }
      ],
      "Tier5Skills": [
        {
          "ID": 1249,
          "Name": "Arcane Bolt Lvl 5",
          "Description": "8 x 55% (440%) magical damage (neutral)",
          "IsBaseAction": true,
          "BaseActionProperties": {
            "Tier": 5,
            "Ultimate": false,
            "Mana": 180,
            "TargetType": 0,
            "Duration": 2.5,
            "IsDefaultAction": false,
            "Tooltip": "",
            "ParentAction": 627,
            "SpecialAttackAnimation": false,
            "IsPotion": false
          },
          "IsActionModifier": true,
          "ActionModifierProperties": {},
          "IsActionDamage": true,
          "ActionDamageProperties": {
            "DamageMultiplicator": 0.55,
            "TotalDamage": 4.4,
            "CalculatedDamage": 0.548812,
            "CalculatedTotalDamage": 4.390496,
            "HitTimings": [
              0.5,
              0.75,
              1.0,
              1.25,
              1.5,
              1.75,
              2.0,
              2.25
            ],
            "Element": 0,
            "Type": 1,
            "FlashDuration": 0.2,
            "MultipleEnemiesDelay": 0.2,
            "CritDamageBonus": 0.0,
            "DefenseBypass": 0.0,
            "DefenseBypassBurnCondition": false,
            "PlayHitAnimation": true,
            "TriggersBleed": false,
            "CannotBeDodged": false,
            "TriggersAllShocks": false,
            "LifestealAmount": 0.0,
            "GravityMultiplier": 0.0,
            "BuffMultiplier": 0.0
          }
        },
        {
          "ID": 1285,
          "Name": "Ice Storm Lvl 3",
          "Description": "2 x 130% (260%) magical damage (water) Hits all enemies, 50% chance to apply Chill (Debuff)",
          "IsBaseAction": true,
          "BaseActionProperties": {
            "Tier": 5,
            "Ultimate": false,
            "Mana": 230,
            "TargetType": 1,
            "Duration": 3.0,
            "IsDefaultAction": false,
            "Tooltip": "",
            "ParentAction": 626,
            "SpecialAttackAnimation": false,
            "IsPotion": false
          },
          "IsActionModifier": true,
          "ActionModifierProperties": {},
          "IsActionDamage": true,
          "ActionDamageProperties": {
            "DamageMultiplicator": 1.3,
            "TotalDamage": 2.6,
            "CalculatedDamage": 1.29417741,
            "CalculatedTotalDamage": 2.58835483,
            "HitTimings": [
              2.0,
              2.5
            ],
            "Element": 2,
            "Type": 1,
            "FlashDuration": 0.4,
            "MultipleEnemiesDelay": 0.2,
            "CritDamageBonus": 0.0,
            "DefenseBypass": 0.0,
            "DefenseBypassBurnCondition": false,
            "PlayHitAnimation": false,
            "TriggersBleed": false,
            "CannotBeDodged": false,
            "TriggersAllShocks": false,
            "LifestealAmount": 0.0,
            "GravityMultiplier": 0.0,
            "BuffMultiplier": 0.0
          },
          "IsActionDebuff": true,
          "ActionDebuffProperties": {
            "Debuffs": [
              3
            ],
            "ApplyDelay": 0.8,
            "ApplyChance": 0.5,
            "TargetCount": 1
          }
        },
        {
          "ID": 382,
          "Name": "Icy Skin",
          "Description": "When this Monster gets attacked, 50% chance to apply Chill on the attacker.",
          "IsPassiveSkill": true,
          "PassiveSkillProperties": {
            "OverlayDebuffs": [
              3
            ],
            "Description": "When this Monster gets attacked, {0%} chance to apply {Chill} on the attacker.",
            "IsAura": false,
            "IsUnique": false
          },
          "IsPassiveDebuffOnGettingHit": true,
          "PassiveDebuffOnGettingHitProperties": {
            "Debuff": 3,
            "Chance": 0.5
          }
        },
        {
          "ID": 155,
          "Name": "Cooling",
          "Description": "Every hit has a 10% chance to apply Chill.",
          "IsPassiveSkill": true,
          "PassiveSkillProperties": {
            "OverlayDebuffs": [
              3
            ],
            "Description": "Every hit has a {0%} chance to apply {Chill}.",
            "IsAura": false,
            "IsUnique": false
          },
          "IsPassiveDebuffChance": true,
          "PassiveDebuffChanceProperties": {
            "IsOnActionDamageHit": true,
            "IsOnCounterAttackHit": true,
            "Debuff": 3,
            "Chance": 0.1,
            "RestrictToElement": false,
            "ElementRestriction": 0
          }
        },
        {
          "ID": 125,
          "Name": "Protector",
          "Description": "Aura: All Monsters in the party receive 7.5% less damage.",
          "IsPassiveSkill": true,
          "PassiveSkillProperties": {
            "Description": "All Monsters in the party receive {0%} less damage.",
            "IsAura": true,
            "IsUnique": false
          },
          "IsPassiveProtector": true,
          "PassiveProtectorProperties": {
            "IsOnCalculateTeamMonsterStats": true,
            "IsOnAllyMonsterUpkeep": true,
            "damageReduction": 0.075,
            "MonsterType": 0,
            "MonsterType2": 0,
            "OnlyMassAttacks": false,
            "AppliesRandomBuff": false
          }
        }
      ]
    },
    {
      "Tier1Skills": [
        {
          "ID": 611,
          "Name": "Chilling Wind",
          "Description": "4 x 40% (160%) magical damage (wind) Applies Chill (Debuff)",
          "IsBaseAction": true,
          "BaseActionProperties": {
            "Tier": 1,
            "Ultimate": false,
            "Mana": 60,
            "TargetType": 0,
            "Duration": 2.0,
            "IsDefaultAction": false,
            "Tooltip": "",
            "ParentAction": null,
            "SpecialAttackAnimation": false,
            "IsPotion": false
          },
          "IsActionModifier": true,
          "ActionModifierProperties": {},
          "IsActionDamage": true,
          "ActionDamageProperties": {
            "DamageMultiplicator": 0.4,
            "TotalDamage": 1.6,
            "CalculatedDamage": 0.4,
            "CalculatedTotalDamage": 1.6,
            "HitTimings": [
              0.5,
              0.8,
              1.1,
              1.4
            ],
            "Element": 3,
            "Type": 1,
            "FlashDuration": 0.4,
            "MultipleEnemiesDelay": 0.2,
            "CritDamageBonus": 0.0,
            "DefenseBypass": 0.0,
            "DefenseBypassBurnCondition": false,
            "PlayHitAnimation": true,
            "TriggersBleed": false,
            "CannotBeDodged": false,
            "TriggersAllShocks": false,
            "LifestealAmount": 0.0,
            "GravityMultiplier": 0.0,
            "BuffMultiplier": 0.0
          },
          "IsActionDebuff": true,
          "ActionDebuffProperties": {
            "Debuffs": [
              3
            ],
            "ApplyDelay": 1.7,
            "ApplyChance": 1.0,
            "TargetCount": 1
          }
        }
      ],
      "Tier2Skills": [
        {
          "ID": 613,
          "Name": "Chilling Wind Lvl 2",
          "Description": "5 x 40% (200%) magical damage (wind) Applies Chill (Debuff)",
          "IsBaseAction": true,
          "BaseActionProperties": {
            "Tier": 2,
            "Ultimate": false,
            "Mana": 90,
            "TargetType": 0,
            "Duration": 2.1,
            "IsDefaultAction": false,
            "Tooltip": "",
            "ParentAction": 611,
            "SpecialAttackAnimation": false,
            "IsPotion": false
          },
          "IsActionModifier": true,
          "ActionModifierProperties": {},
          "IsActionDamage": true,
          "ActionDamageProperties": {
            "DamageMultiplicator": 0.4,
            "TotalDamage": 2.0,
            "CalculatedDamage": 0.408,
            "CalculatedTotalDamage": 2.04,
            "HitTimings": [
              0.4,
              0.7,
              1.0,
              1.3,
              1.6
            ],
            "Element": 3,
            "Type": 1,
            "FlashDuration": 0.4,
            "MultipleEnemiesDelay": 0.2,
            "CritDamageBonus": 0.0,
            "DefenseBypass": 0.0,
            "DefenseBypassBurnCondition": false,
            "PlayHitAnimation": true,
            "TriggersBleed": false,
            "CannotBeDodged": false,
            "TriggersAllShocks": false,
            "LifestealAmount": 0.0,
            "GravityMultiplier": 0.0,
            "BuffMultiplier": 0.0
          },
          "IsActionDebuff": true,
          "ActionDebuffProperties": {
            "Debuffs": [
              3
            ],
            "ApplyDelay": 1.8,
            "ApplyChance": 1.0,
            "TargetCount": 1
          }
        },
        {
          "ID": 174,
          "Name": "Sidekick",
          "Description": "Applies Sidekick (Buff) to whole party",
          "IsBaseAction": true,
          "BaseActionProperties": {
            "Tier": 1,
            "Ultimate": false,
            "Mana": 60,
            "TargetType": 4,
            "Duration": 1.5,
            "IsDefaultAction": false,
            "Tooltip": "",
            "ParentAction": null,
            "SpecialAttackAnimation": false,
            "IsPotion": false
          },
          "IsActionModifier": true,
          "ActionModifierProperties": {},
          "IsActionBuff": true,
          "ActionBuffProperties": {
            "Buffs": [
              3
            ],
            "ApplyDelay": 1.0,
            "SecondaryBuffCount": 3,
            "RandomBuffCount": 0
          }
        },
        {
          "ID": 242,
          "Name": "Defense Plus",
          "Description": "Improve Defense rating by 1 (Increases Defense by 36)",
          "IsPassiveSkill": true,
          "PassiveSkillProperties": {
            "Description": "",
            "IsAura": false,
            "IsUnique": false
          },
          "IsPassiveImproveStat": true,
          "PassiveImproveStatProperties": {
            "IsOnCalculateBaseStats": true,
            "IsOnCalculateStats": true,
            "Stat": 2,
            "Value": 1.0,
            "IsPercent": false,
            "IsNegative": false
          }
        }
      ],
      "Tier3Skills": [
        {
          "ID": 614,
          "Name": "Chilling Wind Lvl 3",
          "Description": "5 x 55% (275%) magical damage (wind) Applies Chill (Debuff)",
          "IsBaseAction": true,
          "BaseActionProperties": {
            "Tier": 3,
            "Ultimate": false,
            "Mana": 120,
            "TargetType": 0,
            "Duration": 2.1,
            "IsDefaultAction": false,
            "Tooltip": "",
            "ParentAction": 613,
            "SpecialAttackAnimation": false,
            "IsPotion": false
          },
          "IsActionModifier": true,
          "ActionModifierProperties": {},
          "IsActionDamage": true,
          "ActionDamageProperties": {
            "DamageMultiplicator": 0.55,
            "TotalDamage": 2.75,
            "CalculatedDamage": 0.5282999,
            "CalculatedTotalDamage": 2.64149976,
            "HitTimings": [
              0.4,
              0.7,
              1.0,
              1.3,
              1.6
            ],
            "Element": 3,
            "Type": 1,
            "FlashDuration": 0.4,
            "MultipleEnemiesDelay": 0.2,
            "CritDamageBonus": 0.0,
            "DefenseBypass": 0.0,
            "DefenseBypassBurnCondition": false,
            "PlayHitAnimation": true,
            "TriggersBleed": false,
            "CannotBeDodged": false,
            "TriggersAllShocks": false,
            "LifestealAmount": 0.0,
            "GravityMultiplier": 0.0,
            "BuffMultiplier": 0.0
          },
          "IsActionDebuff": true,
          "ActionDebuffProperties": {
            "Debuffs": [
              3
            ],
            "ApplyDelay": 1.8,
            "ApplyChance": 1.0,
            "TargetCount": 1
          }
        },
        {
          "ID": 604,
          "Name": "Apprentice",
          "Description": "Applies Sidekick (Buff) to whole party Applies Spellshield (Buff) to a random Monster.",
          "IsBaseAction": true,
          "BaseActionProperties": {
            "Tier": 1,
            "Ultimate": false,
            "Mana": 80,
            "TargetType": 4,
            "Duration": 1.7,
            "IsDefaultAction": false,
            "Tooltip": "",
            "ParentAction": 174,
            "SpecialAttackAnimation": false,
            "IsPotion": false
          },
          "IsActionModifier": true,
          "ActionModifierProperties": {},
          "IsActionBuff": true,
          "ActionBuffProperties": {
            "Buffs": [
              3,
              7
            ],
            "ApplyDelay": 0.8,
            "SecondaryBuffCount": 1,
            "RandomBuffCount": 0
          }
        },
        {
          "ID": 619,
          "Name": "Sub Zero",
          "Description": "Unique Aura: Chill causes enemies affected by it to take 10% increased damage.",
          "IsPassiveSkill": true,
          "PassiveSkillProperties": {
            "Description": "{Chill} causes enemies affected by it to take {0%} increased damage.",
            "IsAura": true,
            "IsUnique": true
          },
          "IsPassiveSubZero": true,
          "PassiveSubZeroProperties": {
            "IsOnAllyActionDamageHit": true,
            "IsOnAllyCounterAttackHit": true,
            "DamageBonus": 0.1
          }
        },
        {
          "ID": 1099,
          "Name": "Defense Overload",
          "Description": "Increase Attack and Magic by 15% of this Monster's Defense.",
          "IsPassiveSkill": true,
          "PassiveSkillProperties": {
            "Description": "Increase Attack and Magic by {0%} of this Monster's Defense.",
            "IsAura": false,
            "IsUnique": false
          },
          "IsPassiveImproveStatDependant": true,
          "PassiveImproveStatDependantProperties": {
            "IsOnCalculateStatsPostMultiplication": true,
            "IsOnCalculateTeamMonsterStats": true,
            "DependantStat": 2,
            "IncreasedStat": 8,
            "Value": 0.15,
            "Pass": 1
          }
        }
      ],
      "Tier4Skills": [
        {
          "ID": 625,
          "Name": "Chilling Wind Lvl 4",
          "Description": "6 x 55% (330%) magical damage (wind) Applies Chill (Debuff)",
          "IsBaseAction": true,
          "BaseActionProperties": {
            "Tier": 4,
            "Ultimate": false,
            "Mana": 160,
            "TargetType": 0,
            "Duration": 2.2,
            "IsDefaultAction": false,
            "Tooltip": "",
            "ParentAction": 614,
            "SpecialAttackAnimation": false,
            "IsPotion": false
          },
          "IsActionModifier": true,
          "ActionModifierProperties": {},
          "IsActionDamage": true,
          "ActionDamageProperties": {
            "DamageMultiplicator": 0.55,
            "TotalDamage": 3.30000019,
            "CalculatedDamage": 0.553212464,
            "CalculatedTotalDamage": 3.319275,
            "HitTimings": [
              0.4,
              0.65,
              0.9,
              1.15,
              1.4,
              1.65
            ],
            "Element": 3,
            "Type": 1,
            "FlashDuration": 0.4,
            "MultipleEnemiesDelay": 0.2,
            "CritDamageBonus": 0.0,
            "DefenseBypass": 0.0,
            "DefenseBypassBurnCondition": false,
            "PlayHitAnimation": true,
            "TriggersBleed": false,
            "CannotBeDodged": false,
            "TriggersAllShocks": false,
            "LifestealAmount": 0.0,
            "GravityMultiplier": 0.0,
            "BuffMultiplier": 0.0
          },
          "IsActionDebuff": true,
          "ActionDebuffProperties": {
            "Debuffs": [
              3
            ],
            "ApplyDelay": 1.9,
            "ApplyChance": 1.0,
            "TargetCount": 1
          }
        },
        {
          "ID": 605,
          "Name": "Apprentice Lvl 2",
          "Description": "Applies Sidekick (Buff) to whole party Applies Spellshield (Buff) to two random Monsters.",
          "IsBaseAction": true,
          "BaseActionProperties": {
            "Tier": 1,
            "Ultimate": false,
            "Mana": 110,
            "TargetType": 4,
            "Duration": 1.7,
            "IsDefaultAction": false,
            "Tooltip": "",
            "ParentAction": 604,
            "SpecialAttackAnimation": false,
            "IsPotion": false
          },
          "IsActionModifier": true,
          "ActionModifierProperties": {},
          "IsActionBuff": true,
          "ActionBuffProperties": {
            "Buffs": [
              3,
              7
            ],
            "ApplyDelay": 0.8,
            "SecondaryBuffCount": 2,
            "RandomBuffCount": 0
          }
        },
        {
          "ID": 251,
          "Name": "Double Impact",
          "Description": "When exploiting an enemy's weakness with an attack, trigger an additional 50% damage hit.",
          "IsPassiveSkill": true,
          "PassiveSkillProperties": {
            "Description": "When exploiting an enemy's weakness with an attack, trigger an additional {0%} damage hit.",
            "IsAura": false,
            "IsUnique": false
          },
          "IsPassiveDoubleImpact": true,
          "PassiveDoubleImpactProperties": {
            "IsOnActionDamageStarted": true,
            "DamageValue": 0.5,
            "AnimElementFire": null,
            "AnimElementWater": null,
            "AnimElementWind": null,
            "AnimElementEarth": null,
            "AnimElementNeutral": null
          }
        },
        {
          "ID": 242,
          "Name": "Defense Plus",
          "Description": "Improve Defense rating by 1 (Increases Defense by 36)",
          "IsPassiveSkill": true,
          "PassiveSkillProperties": {
            "Description": "",
            "IsAura": false,
            "IsUnique": false
          },
          "IsPassiveImproveStat": true,
          "PassiveImproveStatProperties": {
            "IsOnCalculateBaseStats": true,
            "IsOnCalculateStats": true,
            "Stat": 2,
            "Value": 1.0,
            "IsPercent": false,
            "IsNegative": false
          }
        }
      ],
      "Tier5Skills": [
        {
          "ID": 1295,
          "Name": "Chilling Wind Lvl 5",
          "Description": "6 x 75% (450%) magical damage (wind) Applies Chill (Debuff)",
          "IsBaseAction": true,
          "BaseActionProperties": {
            "Tier": 5,
            "Ultimate": false,
            "Mana": 220,
            "TargetType": 0,
            "Duration": 2.2,
            "IsDefaultAction": false,
            "Tooltip": "",
            "ParentAction": 625,
            "SpecialAttackAnimation": false,
            "IsPotion": false
          },
          "IsActionModifier": true,
          "ActionModifierProperties": {},
          "IsActionDamage": true,
          "ActionDamageProperties": {
            "DamageMultiplicator": 0.75,
            "TotalDamage": 4.5,
            "CalculatedDamage": 0.7318742,
            "CalculatedTotalDamage": 4.39124537,
            "HitTimings": [
              0.4,
              0.65,
              0.9,
              1.15,
              1.4,
              1.65
            ],
            "Element": 3,
            "Type": 1,
            "FlashDuration": 0.4,
            "MultipleEnemiesDelay": 0.2,
            "CritDamageBonus": 0.0,
            "DefenseBypass": 0.0,
            "DefenseBypassBurnCondition": false,
            "PlayHitAnimation": true,
            "TriggersBleed": false,
            "CannotBeDodged": false,
            "TriggersAllShocks": false,
            "LifestealAmount": 0.0,
            "GravityMultiplier": 0.0,
            "BuffMultiplier": 0.0
          },
          "IsActionDebuff": true,
          "ActionDebuffProperties": {
            "Debuffs": [
              3
            ],
            "ApplyDelay": 1.9,
            "ApplyChance": 1.0,
            "TargetCount": 1
          }
        },
        {
          "ID": 768,
          "Name": "Apprentice Lvl 3",
          "Description": "Applies Sidekick & Spellshield (Buffs) to whole party",
          "IsBaseAction": true,
          "BaseActionProperties": {
            "Tier": 1,
            "Ultimate": false,
            "Mana": 150,
            "TargetType": 4,
            "Duration": 1.8,
            "IsDefaultAction": false,
            "Tooltip": "",
            "ParentAction": 605,
            "SpecialAttackAnimation": false,
            "IsPotion": false
          },
          "IsActionModifier": true,
          "ActionModifierProperties": {},
          "IsActionBuff": true,
          "ActionBuffProperties": {
            "Buffs": [
              3,
              7
            ],
            "ApplyDelay": 0.8,
            "SecondaryBuffCount": 3,
            "RandomBuffCount": 0
          }
        },
        {
          "ID": 1835,
          "Name": "Anti Curse",
          "Description": "Aura: All Debuffs are 20% less effective on Monsters in your party.",
          "IsPassiveSkill": true,
          "PassiveSkillProperties": {
            "Description": "All Debuffs are {0%} less effective on Monsters in your party.",
            "IsAura": true,
            "IsUnique": false
          },
          "IsPassiveAntiCurse": true,
          "PassiveAntiCurseProperties": {
            "IsOnCalculateTeamMonsterStats": true,
            "Modifier": 0.2
          }
        },
        {
          "ID": 385,
          "Name": "Defense Proc",
          "Description": "Every attack triggers an additional hit equal to 50% of Defense value.",
          "IsPassiveSkill": true,
          "PassiveSkillProperties": {
            "Description": "Every attack triggers an additional hit equal to {1%} of Defense value.",
            "IsAura": false,
            "IsUnique": false
          },
          "IsPassiveComboMaster": true,
          "PassiveComboMasterProperties": {
            "IsOnAllyActionDamageStarted": true,
            "DamageValue": 0.0,
            "StatScaling": 0.5,
            "ScaleStat": 2,
            "AnimElement": null,
            "ElementRestriction": 8,
            "TypeRestriction": 0
          }
        }
      ]
    },
    {
      "Tier1Skills": [
        {
          "ID": 1680,
          "Name": "Restoring Shield",
          "Description": "Shield target for 4 x (50 + 15% Defense) Removes 1 Debuff",
          "IsBaseAction": true,
          "BaseActionProperties": {
            "Tier": 1,
            "Ultimate": false,
            "Mana": 50,
            "TargetType": 3,
            "Duration": 2.4,
            "IsDefaultAction": false,
            "Tooltip": "",
            "ParentAction": null,
            "SpecialAttackAnimation": false,
            "IsPotion": false
          },
          "IsActionModifier": true,
          "ActionModifierProperties": {},
          "IsActionRemoveDebuff": true,
          "ActionRemoveDebuffProperties": {
            "Count": 1,
            "Delay": 2.1
          },
          "IsActionShield": true,
          "ActionShieldProperties": {
            "ShieldAmount": 50.0,
            "ScaleDefense": 0.15,
            "ScaleMagic": 0.0,
            "ScaleAttack": 0.0,
            "ScaleMana": 0.0,
            "ScaleTargetHealth": 0.0,
            "ShieldTimings": [
              0.9,
              1.2,
              1.5,
              1.8
            ],
            "ShieldCaster": false
          }
        }
      ],
      "Tier2Skills": [
        {
          "ID": 1681,
          "Name": "Restoring Shield Lvl 2",
          "Description": "Shield target for 5 x (60 + 15% Defense) Removes 2 Debuffs",
          "IsBaseAction": true,
          "BaseActionProperties": {
            "Tier": 1,
            "Ultimate": false,
            "Mana": 80,
            "TargetType": 3,
            "Duration": 2.6,
            "IsDefaultAction": false,
            "Tooltip": "",
            "ParentAction": 1680,
            "SpecialAttackAnimation": false,
            "IsPotion": false
          },
          "IsActionModifier": true,
          "ActionModifierProperties": {},
          "IsActionRemoveDebuff": true,
          "ActionRemoveDebuffProperties": {
            "Count": 2,
            "Delay": 2.1
          },
          "IsActionShield": true,
          "ActionShieldProperties": {
            "ShieldAmount": 60.0,
            "ScaleDefense": 0.15,
            "ScaleMagic": 0.0,
            "ScaleAttack": 0.0,
            "ScaleMana": 0.0,
            "ScaleTargetHealth": 0.0,
            "ShieldTimings": [
              0.9,
              1.15,
              1.4,
              1.65,
              1.9
            ],
            "ShieldCaster": false
          }
        },
        {
          "ID": 78,
          "Name": "Health Plus",
          "Description": "Improve Health rating by 1 (Increases Health by 332)",
          "IsPassiveSkill": true,
          "PassiveSkillProperties": {
            "Description": "",
            "IsAura": false,
            "IsUnique": false
          },
          "IsPassiveImproveStat": true,
          "PassiveImproveStatProperties": {
            "IsOnCalculateBaseStats": true,
            "IsOnCalculateStats": true,
            "Stat": 3,
            "Value": 1.0,
            "IsPercent": false,
            "IsNegative": false
          }
        },
        {
          "ID": 212,
          "Name": "Copy Shield",
          "Description": "When Shielding yourself, also apply 20% of that Shield to allies.",
          "IsPassiveSkill": true,
          "PassiveSkillProperties": {
            "Description": "When Shielding yourself, also apply {0%} of that Shield to allies.",
            "IsAura": false,
            "IsUnique": false
          },
          "IsPassiveCopyShield": true,
          "PassiveCopyShieldProperties": {
            "IsOnReceiveShield": true,
            "CopyAmount": 0.2
          }
        },
        {
          "ID": 175,
          "Name": "Mana Plus",
          "Description": "Improve Mana rating by 1 (Increases Mana by 20. Increases Mana Regeneration by 11)",
          "IsPassiveSkill": true,
          "PassiveSkillProperties": {
            "Description": "",
            "IsAura": false,
            "IsUnique": false
          },
          "IsPassiveImproveStat": true,
          "PassiveImproveStatProperties": {
            "IsOnCalculateBaseStats": true,
            "IsOnCalculateStats": true,
            "Stat": 4,
            "Value": 1.0,
            "IsPercent": false,
            "IsNegative": false
          }
        }
      ],
      "Tier3Skills": [
        {
          "ID": 1682,
          "Name": "Restoring Shield Lvl 3",
          "Description": "Shield target for 6 x (75 + 15% Defense) Removes 2 Debuffs",
          "IsBaseAction": true,
          "BaseActionProperties": {
            "Tier": 1,
            "Ultimate": false,
            "Mana": 120,
            "TargetType": 3,
            "Duration": 2.7,
            "IsDefaultAction": false,
            "Tooltip": "",
            "ParentAction": 1681,
            "SpecialAttackAnimation": false,
            "IsPotion": false
          },
          "IsActionModifier": true,
          "ActionModifierProperties": {},
          "IsActionRemoveDebuff": true,
          "ActionRemoveDebuffProperties": {
            "Count": 2,
            "Delay": 2.3
          },
          "IsActionShield": true,
          "ActionShieldProperties": {
            "ShieldAmount": 75.0,
            "ScaleDefense": 0.15,
            "ScaleMagic": 0.0,
            "ScaleAttack": 0.0,
            "ScaleMana": 0.0,
            "ScaleTargetHealth": 0.0,
            "ShieldTimings": [
              0.9,
              1.15,
              1.4,
              1.65,
              1.9,
              2.15
            ],
            "ShieldCaster": false
          }
        },
        {
          "ID": 78,
          "Name": "Health Plus",
          "Description": "Improve Health rating by 1 (Increases Health by 332)",
          "IsPassiveSkill": true,
          "PassiveSkillProperties": {
            "Description": "",
            "IsAura": false,
            "IsUnique": false
          },
          "IsPassiveImproveStat": true,
          "PassiveImproveStatProperties": {
            "IsOnCalculateBaseStats": true,
            "IsOnCalculateStats": true,
            "Stat": 3,
            "Value": 1.0,
            "IsPercent": false,
            "IsNegative": false
          }
        },
        {
          "ID": 621,
          "Name": "Shield Aura",
          "Description": "Aura: All Shield effects of Monsters in the party are increased by 10%.",
          "IsPassiveSkill": true,
          "PassiveSkillProperties": {
            "Description": "All Shield effects of Monsters in the party are increased by {0%}.",
            "IsAura": true,
            "IsUnique": false
          },
          "IsPassiveShieldAura": true,
          "PassiveShieldAuraProperties": {
            "IsOnCalculateTeamMonsterStats": true,
            "ShieldBonus": 0.1
          }
        },
        {
          "ID": 242,
          "Name": "Defense Plus",
          "Description": "Improve Defense rating by 1 (Increases Defense by 36)",
          "IsPassiveSkill": true,
          "PassiveSkillProperties": {
            "Description": "",
            "IsAura": false,
            "IsUnique": false
          },
          "IsPassiveImproveStat": true,
          "PassiveImproveStatProperties": {
            "IsOnCalculateBaseStats": true,
            "IsOnCalculateStats": true,
            "Stat": 2,
            "Value": 1.0,
            "IsPercent": false,
            "IsNegative": false
          }
        }
      ],
      "Tier4Skills": [
        {
          "ID": 1683,
          "Name": "Restoring Shield Lvl 4",
          "Description": "Shield target for 6 x (100 + 15% Defense) Removes 3 Debuffs",
          "IsBaseAction": true,
          "BaseActionProperties": {
            "Tier": 1,
            "Ultimate": false,
            "Mana": 160,
            "TargetType": 3,
            "Duration": 2.7,
            "IsDefaultAction": false,
            "Tooltip": "",
            "ParentAction": 1682,
            "SpecialAttackAnimation": false,
            "IsPotion": false
          },
          "IsActionModifier": true,
          "ActionModifierProperties": {},
          "IsActionRemoveDebuff": true,
          "ActionRemoveDebuffProperties": {
            "Count": 3,
            "Delay": 2.3
          },
          "IsActionShield": true,
          "ActionShieldProperties": {
            "ShieldAmount": 100.0,
            "ScaleDefense": 0.15,
            "ScaleMagic": 0.0,
            "ScaleAttack": 0.0,
            "ScaleMana": 0.0,
            "ScaleTargetHealth": 0.0,
            "ShieldTimings": [
              0.9,
              1.15,
              1.4,
              1.65,
              1.9,
              2.15
            ],
            "ShieldCaster": false
          }
        },
        {
          "ID": 1678,
          "Name": "Ice Shield",
          "Description": "Shield all for 2 x (200 + 20% Defense + 20% Magic) Applies Chill (Debuff) to a random enemy",
          "IsBaseAction": true,
          "BaseActionProperties": {
            "Tier": 4,
            "Ultimate": false,
            "Mana": 160,
            "TargetType": 4,
            "Duration": 2.6,
            "IsDefaultAction": false,
            "Tooltip": "",
            "ParentAction": null,
            "SpecialAttackAnimation": false,
            "IsPotion": false
          },
          "IsActionModifier": true,
          "ActionModifierProperties": {},
          "IsActionDebuff": true,
          "ActionDebuffProperties": {
            "Debuffs": [
              3
            ],
            "ApplyDelay": 2.4,
            "ApplyChance": 1.0,
            "TargetCount": 1
          },
          "IsActionShield": true,
          "ActionShieldProperties": {
            "ShieldAmount": 200.0,
            "ScaleDefense": 0.2,
            "ScaleMagic": 0.2,
            "ScaleAttack": 0.0,
            "ScaleMana": 0.0,
            "ScaleTargetHealth": 0.0,
            "ShieldTimings": [
              1.2,
              1.7
            ],
            "ShieldCaster": false
          }
        },
        {
          "ID": 428,
          "Name": "Combo Shielding",
          "Description": "Upon using a Shield action, additionally Shield an ally with the lowest Shield by 50% of this Monster's Defense.",
          "IsPassiveSkill": true,
          "PassiveSkillProperties": {
            "Description": "Upon using a Shield action, additionally Shield an ally with the lowest Shield by {0%} of this Monster's Defense.",
            "IsAura": false,
            "IsUnique": false
          },
          "IsPassiveComboShielding": true,
          "PassiveComboShieldingProperties": {
            "IsOnActionShieldStarted": true,
            "DefenseScale": 0.5
          }
        },
        {
          "ID": 175,
          "Name": "Mana Plus",
          "Description": "Improve Mana rating by 1 (Increases Mana by 20. Increases Mana Regeneration by 11)",
          "IsPassiveSkill": true,
          "PassiveSkillProperties": {
            "Description": "",
            "IsAura": false,
            "IsUnique": false
          },
          "IsPassiveImproveStat": true,
          "PassiveImproveStatProperties": {
            "IsOnCalculateBaseStats": true,
            "IsOnCalculateStats": true,
            "Stat": 4,
            "Value": 1.0,
            "IsPercent": false,
            "IsNegative": false
          }
        }
      ],
      "Tier5Skills": [
        {
          "ID": 1684,
          "Name": "Restoring Shield Lvl 5",
          "Description": "Shield target for 7 x (125 + 15% Defense) Removes 4 Debuffs",
          "IsBaseAction": true,
          "BaseActionProperties": {
            "Tier": 1,
            "Ultimate": false,
            "Mana": 210,
            "TargetType": 3,
            "Duration": 3.2,
            "IsDefaultAction": false,
            "Tooltip": "",
            "ParentAction": 1683,
            "SpecialAttackAnimation": false,
            "IsPotion": false
          },
          "IsActionModifier": true,
          "ActionModifierProperties": {},
          "IsActionRemoveDebuff": true,
          "ActionRemoveDebuffProperties": {
            "Count": 4,
            "Delay": 2.5
          },
          "IsActionShield": true,
          "ActionShieldProperties": {
            "ShieldAmount": 125.0,
            "ScaleDefense": 0.15,
            "ScaleMagic": 0.0,
            "ScaleAttack": 0.0,
            "ScaleMana": 0.0,
            "ScaleTargetHealth": 0.0,
            "ShieldTimings": [
              0.8,
              1.05,
              1.3,
              1.55,
              1.8,
              2.05,
              2.3
            ],
            "ShieldCaster": false
          }
        },
        {
          "ID": 1679,
          "Name": "Ice Shield Lvl 2",
          "Description": "Shield all for 2 x (300 + 25% Defense + 25% Magic) Applies Chill (Debuff) to 2 random enemies",
          "IsBaseAction": true,
          "BaseActionProperties": {
            "Tier": 5,
            "Ultimate": false,
            "Mana": 220,
            "TargetType": 4,
            "Duration": 2.8,
            "IsDefaultAction": false,
            "Tooltip": "",
            "ParentAction": 1678,
            "SpecialAttackAnimation": false,
            "IsPotion": false
          },
          "IsActionModifier": true,
          "ActionModifierProperties": {},
          "IsActionDebuff": true,
          "ActionDebuffProperties": {
            "Debuffs": [
              3
            ],
            "ApplyDelay": 2.2,
            "ApplyChance": 1.0,
            "TargetCount": 2
          },
          "IsActionShield": true,
          "ActionShieldProperties": {
            "ShieldAmount": 300.0,
            "ScaleDefense": 0.25,
            "ScaleMagic": 0.25,
            "ScaleAttack": 0.0,
            "ScaleMana": 0.0,
            "ScaleTargetHealth": 0.0,
            "ShieldTimings": [
              1.2,
              1.7
            ],
            "ShieldCaster": false
          }
        },
        {
          "ID": 1140,
          "Name": "Defensive Presence",
          "Description": "At the beginning of your turn, a random Monster in the party gains Barrier (Buff).",
          "IsPassiveSkill": true,
          "PassiveSkillProperties": {
            "OverlayBuffs": [
              8
            ],
            "Description": "At the beginning of your turn, a random Monster in the party gains {Barrier} (Buff).",
            "IsAura": false,
            "IsUnique": false
          },
          "IsPassiveStartTurnBuff": true,
          "PassiveStartTurnBuffProperties": {
            "IsOnMonsterUpkeep": true,
            "BuffType": 8
          }
        },
        {
          "ID": 121,
          "Name": "Magic Powered Shield",
          "Description": "At the start of combat, apply a Shield equal to 150% of Magic value.",
          "IsPassiveSkill": true,
          "PassiveSkillProperties": {
            "Description": "At the start of combat, apply a Shield equal to {0%} of Magic value.",
            "IsAura": false,
            "IsUnique": false
          },
          "IsPassiveStartCombatShield": true,
          "PassiveStartCombatShieldProperties": {
            "IsOnCombatStart": true,
            "IsOnAllyCombatStart": true,
            "IsOnCalculateTeamMonsterStats": true,
            "Stat": 1,
            "DualStat": false,
            "SecondaryStat": 0,
            "Percent": 1.5,
            "TypeRestriction": 0,
            "TriggerForBackupMonsters": false,
            "BasedOnCastersStat": false,
            "DamageReduction": 0.0,
            "PerHealth": 0
          }
        }
      ]
    }
  ],
  "Ultimates": [
    {
      "ID": 1713,
      "Name": "Blizzard",
      "Description": "3 x 100% (300%) magical damage (water) Hits all enemies, every hit has a 20% chance to apply Chill (Debuff).",
      "IsBaseAction": true,
      "BaseActionProperties": {
        "Tier": 6,
        "Ultimate": true,
        "Mana": 240,
        "TargetType": 1,
        "Duration": 4.0,
        "IsDefaultAction": false,
        "Tooltip": "",
        "ParentAction": null,
        "SpecialAttackAnimation": false,
        "IsPotion": false
      },
      "IsActionModifier": true,
      "ActionModifierProperties": {},
      "IsActionDamage": true,
      "ActionDamageProperties": {
        "DamageMultiplicator": 1.0,
        "TotalDamage": 3.0,
        "CalculatedDamage": 0.9616794,
        "CalculatedTotalDamage": 2.88503814,
        "HitTimings": [
          1.3,
          2.3,
          3.3
        ],
        "Element": 2,
        "Type": 1,
        "FlashDuration": 0.4,
        "MultipleEnemiesDelay": 0.2,
        "CritDamageBonus": 0.0,
        "DefenseBypass": 0.0,
        "DefenseBypassBurnCondition": false,
        "PlayHitAnimation": false,
        "TriggersBleed": false,
        "CannotBeDodged": false,
        "TriggersAllShocks": false,
        "LifestealAmount": 0.0,
        "GravityMultiplier": 0.0,
        "BuffMultiplier": 0.0
      },
      "IsActionDebuffOnHit": true,
      "ActionDebuffOnHitProperties": {
        "Debuff": 3,
        "dualDebuff": false,
        "Debuff2": 0,
        "ApplyChance": 0.2
      }
    },
    {
      "ID": 1767,
      "Name": "Arcane Barrage",
      "Description": "10 x 65% (650%) magical damage (neutral) Shield self for 1 x (750 + 200% Max Mana)",
      "IsBaseAction": true,
      "BaseActionProperties": {
        "Tier": 6,
        "Ultimate": true,
        "Mana": 220,
        "TargetType": 0,
        "Duration": 3.4,
        "IsDefaultAction": false,
        "Tooltip": "",
        "ParentAction": null,
        "SpecialAttackAnimation": false,
        "IsPotion": false
      },
      "IsActionModifier": true,
      "ActionModifierProperties": {},
      "IsActionDamage": true,
      "ActionDamageProperties": {
        "DamageMultiplicator": 0.65,
        "TotalDamage": 6.5,
        "CalculatedDamage": 0.513591349,
        "CalculatedTotalDamage": 5.13591337,
        "HitTimings": [
          0.5,
          0.75,
          1.0,
          1.25,
          1.5,
          1.75,
          2.0,
          2.25,
          2.5,
          2.75
        ],
        "Element": 0,
        "Type": 1,
        "FlashDuration": 0.2,
        "MultipleEnemiesDelay": 0.2,
        "CritDamageBonus": 0.0,
        "DefenseBypass": 0.0,
        "DefenseBypassBurnCondition": false,
        "PlayHitAnimation": true,
        "TriggersBleed": false,
        "CannotBeDodged": false,
        "TriggersAllShocks": false,
        "LifestealAmount": 0.0,
        "GravityMultiplier": 0.0,
        "BuffMultiplier": 0.0
      },
      "IsActionShield": true,
      "ActionShieldProperties": {
        "ShieldAmount": 750.0,
        "ScaleDefense": 0.0,
        "ScaleMagic": 0.0,
        "ScaleAttack": 0.0,
        "ScaleMana": 2.0,
        "ScaleTargetHealth": 0.0,
        "ShieldTimings": [
          3.1
        ],
        "ShieldCaster": true
      }
    },
    {
      "ID": 1749,
      "Name": "Aurora's Shield",
      "Description": "Shield all for 3 x (300 + 25% Defense) Removes 2 Debuffs from all allies",
      "IsBaseAction": true,
      "BaseActionProperties": {
        "Tier": 6,
        "Ultimate": true,
        "Mana": 220,
        "TargetType": 4,
        "Duration": 3.4,
        "IsDefaultAction": false,
        "Tooltip": "",
        "ParentAction": null,
        "SpecialAttackAnimation": false,
        "IsPotion": false
      },
      "IsActionModifier": true,
      "ActionModifierProperties": {},
      "IsActionRemoveDebuff": true,
      "ActionRemoveDebuffProperties": {
        "Count": 2,
        "Delay": 2.7
      },
      "IsActionShield": true,
      "ActionShieldProperties": {
        "ShieldAmount": 300.0,
        "ScaleDefense": 0.25,
        "ScaleMagic": 0.0,
        "ScaleAttack": 0.0,
        "ScaleMana": 0.0,
        "ScaleTargetHealth": 0.0,
        "ShieldTimings": [
          1.0,
          1.6,
          2.2
        ],
        "ShieldCaster": false
      }
    }
  ],
  "GoldReward": 45,
  "RewardsCommon": [
    {
      "ID": 52,
      "Name": "Potion",
      "Description": "Heal target for 5 x 250",
      "Icon": "",
      "Price": 150,
      "IsCombatConsumable": true,
      "CombatConsumableProperties": {
        "EffectAction": 241,
        "Icon": "icon_potion",
        "Description": "",
        "RetreatItem": false
      }
    },
    {
      "ID": 38,
      "Name": "Iron",
      "Description": "Level 2 common upgrade material",
      "Icon": "",
      "Price": 200,
      "IsCraftMaterial": true,
      "CraftMaterialProperties": {
        "Description": "Level 2 common upgrade material",
        "Level": 2
      }
    }
  ],
  "RewardsRare": [
    {
      "ID": 53,
      "Name": "Blue Gem",
      "Description": "Level 1 rare upgrade material",
      "Icon": "",
      "Price": 250,
      "IsCraftMaterial": true,
      "CraftMaterialProperties": {
        "Description": "Level 1 rare upgrade material",
        "Level": 1
      }
    },
    {
      "ID": 788,
      "Name": "Vital Ring+3",
      "Description": "Health +550",
      "Icon": "",
      "Price": 900,
      "IsEquipment": true,
      "EquipmentProperties": {
        "Type": 4,
        "Icon": "icon_ring",
        "Attack": 0,
        "Magic": 0,
        "Defense": 0,
        "CritChance": 0.0,
        "CritDamage": 0.0,
        "Health": 550,
        "Mana": 0,
        "ManaRegeneration": 0,
        "DamageBonus": 0.0,
        "NonCritDamage": 0.0,
        "HealBonus": 0.0,
        "ShieldBonus": 0.0,
        "DodgeChance": 0.0,
        "Unique": false,
        "OnlyUnshifted": false,
        "OnlyFamiliars": false,
        "UpgradesTo": 901,
        "UpgradeMaterials": [
          {
            "Item": {
              "ID": 804,
              "Name": "Verdant Gem",
              "Description": "Level 3 rare upgrade material",
              "Icon": "",
              "Price": 500,
              "IsCraftMaterial": true,
              "CraftMaterialProperties": {
                "Description": "Level 3 rare upgrade material",
                "Level": 3
              }
            },
            "Quantity": 1
          },
          {
            "Item": {
              "ID": 282,
              "Name": "Silver",
              "Description": "Level 4 rare upgrade material",
              "Icon": "",
              "Price": 750,
              "IsCraftMaterial": true,
              "CraftMaterialProperties": {
                "Description": "Level 4 rare upgrade material",
                "Level": 4
              }
            },
            "Quantity": 1
          }
        ],
        "FullDefenseOffHand": false,
        "IsInstrument": false
      }
    },
    {
      "ID": 612,
      "Name": "Ice Blob Egg",
      "Description": "Consume to hatch: Ice Blob",
      "Icon": "",
      "Price": 400,
      "IsEgg": true,
      "EggProperties": {
        "Monster": 610
      }
    }
  ],
  "NoRareRewards": false,
  "Appearances": [
    {
      "SceneName": "SnowyPeaks_East1",
      "MapAreaName": "Snowy Peaks"
    },
    {
      "SceneName": "SnowyPeaks_East2",
      "MapAreaName": "Snowy Peaks"
    },
    {
      "SceneName": "SnowyPeaks_East3",
      "MapAreaName": "Snowy Peaks"
    },
    {
      "SceneName": "SnowyPeaks_East4",
      "MapAreaName": "Snowy Peaks"
    },
    {
      "SceneName": "SnowyPeaks_East5",
      "MapAreaName": "Snowy Peaks"
    },
    {
      "SceneName": "SnowyPeaks_West1",
      "MapAreaName": "Snowy Peaks"
    },
    {
      "SceneName": "SnowyPeaks_West2",
      "MapAreaName": "Snowy Peaks"
    },
    {
      "SceneName": "SnowyPeaks_WestDark",
      "MapAreaName": "Snowy Peaks"
    },
    {
      "SceneName": "SnowyPeaks_West3",
      "MapAreaName": "Snowy Peaks"
    },
    {
      "SceneName": "SnowyPeaks_West4",
      "MapAreaName": "Snowy Peaks"
    },
    {
      "SceneName": "SnowyPeaks_WestMountain1",
      "MapAreaName": "Snowy Peaks"
    },
    {
      "SceneName": "SnowyPeaks_WestMountain2",
      "MapAreaName": "Snowy Peaks"
    },
    {
      "SceneName": "SnowyPeaks_WestMountain3",
      "MapAreaName": "Snowy Peaks"
    },
    {
      "SceneName": "SnowyPeaks_WestMountain4",
      "MapAreaName": "Snowy Peaks"
    },
    {
      "SceneName": "SnowyPeaks_WestMountain5",
      "MapAreaName": "Snowy Peaks"
    },
    {
      "SceneName": "SnowyPeaks_HighChallenge",
      "MapAreaName": "Snowy Peaks"
    },
    {
      "SceneName": "SnowyPeaks_WestMountain6",
      "MapAreaName": "Snowy Peaks"
    },
    {
      "SceneName": "SnowyPeaks_Bridge",
      "MapAreaName": "Snowy Peaks"
    },
    {
      "SceneName": "SnowyPeaks_WestMountain7",
      "MapAreaName": "Snowy Peaks"
    },
    {
      "SceneName": "SnowyPeaks_WestMountainSecret",
      "MapAreaName": "Snowy Peaks"
    },
    {
      "SceneName": "SnowyPeaks_EastMountain1",
      "MapAreaName": "Snowy Peaks"
    },
    {
      "SceneName": "SnowyPeaks_Lake",
      "MapAreaName": "Snowy Peaks"
    },
    {
      "SceneName": "SnowyPeaks_ChampionRoom",
      "MapAreaName": "Snowy Peaks"
    },
    {
      "SceneName": "SnowyPeaks_EastMountain2",
      "MapAreaName": "Snowy Peaks"
    },
    {
      "SceneName": "SnowyPeaks_EastDark",
      "MapAreaName": "Snowy Peaks"
    },
    {
      "SceneName": "SnowyPeaks_EastMountain3",
      "MapAreaName": "Snowy Peaks"
    },
    {
      "SceneName": "SnowyPeaks_EastMountainClothesmaker",
      "MapAreaName": "Snowy Peaks"
    },
    {
      "SceneName": "SnowyPeaks_EastMountain4",
      "MapAreaName": "Snowy Peaks"
    },
    {
      "SceneName": "SnowyPeaks_EastMountain5",
      "MapAreaName": "Snowy Peaks"
    },
    {
      "SceneName": "SnowyPeaks_ClothesmakerHouse",
      "MapAreaName": "Snowy Peaks"
    },
    {
      "SceneName": "SnowyPeaks_EastMountainTop",
      "MapAreaName": "Snowy Peaks"
    },
    {
      "SceneName": "SnowyPeaks_Cryomancer",
      "MapAreaName": "Snowy Peaks"
    },
    {
      "SceneName": "SnowyPeaks_SunPalaceEntrance",
      "MapAreaName": "Snowy Peaks"
    },
    {
      "SceneName": "SnowyPeaks_West5",
      "MapAreaName": "Snowy Peaks"
    },
    {
      "SceneName": "SnowyPeaks_ChampionRoom2",
      "MapAreaName": "Snowy Peaks"
    },
    {
      "SceneName": "BlobBurg_East1",
      "MapAreaName": "Blob Burg"
    },
    {
      "SceneName": "BlobBurg_East2",
      "MapAreaName": "Blob Burg"
    },
    {
      "SceneName": "BlobBurg_East3",
      "MapAreaName": "Blob Burg"
    },
    {
      "SceneName": "BlobBurg_Center1",
      "MapAreaName": "Blob Burg"
    },
    {
      "SceneName": "BlobBurg_East4",
      "MapAreaName": "Blob Burg"
    },
    {
      "SceneName": "BlobBurg_East5",
      "MapAreaName": "Blob Burg"
    },
    {
      "SceneName": "BlobBurg_Center3",
      "MapAreaName": "Blob Burg"
    },
    {
      "SceneName": "BlobBurg_Worms",
      "MapAreaName": "Blob Burg"
    },
    {
      "SceneName": "BlobBurg_West1",
      "MapAreaName": "Blob Burg"
    },
    {
      "SceneName": "BlobBurg_Center2",
      "MapAreaName": "Blob Burg"
    },
    {
      "SceneName": "BlobBurg_West2",
      "MapAreaName": "Blob Burg"
    },
    {
      "SceneName": "BlobBurg_Center4",
      "MapAreaName": "Blob Burg"
    },
    {
      "SceneName": "BlobBurg_South1",
      "MapAreaName": "Blob Burg"
    },
    {
      "SceneName": "BlobBurg_South2",
      "MapAreaName": "Blob Burg"
    },
    {
      "SceneName": "BlobBurg_Center5",
      "MapAreaName": "Blob Burg"
    },
    {
      "SceneName": "BlobBurg_Champion",
      "MapAreaName": "Blob Burg"
    },
    {
      "SceneName": "BlobBurg_EastHidden",
      "MapAreaName": "Blob Burg"
    }
  ]
}